veriusapigateway/__init__.py
veriusapigateway/test.py
veriusapigateway/veriusapigateway.py
veriusapigateway-0.1.8.dist-info/LICENSE
veriusapigateway-0.1.8.dist-info/METADATA
veriusapigateway-0.1.8.dist-info/WHEEL
veriusapigateway-0.1.8.dist-info/top_level.txt
veriusapigateway-0.1.8.dist-info/RECORD
