Metadata-Version: 2.1
Name: veriusapigateway
Version: 0.1.8
Summary: API Gateway for accessing Verius Web Services.
Home-page: https://bitbucket.org/veriusai/veriusapigateway/
Author: Verius Technologhy
Author-email: info@verius.ai
License: UNKNOWN
Platform: UNKNOWN
Classifier: Programming Language :: Python :: 3
Classifier: Operating System :: OS Independent
